pyramid_precis_creative_template/__init__.py
pyramid_precis_creative_template/models.py
pyramid_precis_creative_template/static/css/creative.css
pyramid_precis_creative_template/static/css/resume.css
pyramid_precis_creative_template/static/css/theme.css
pyramid_precis_creative_template/static/favicon_io/about.txt
pyramid_precis_creative_template/static/favicon_io/android-chrome-192x192.png
pyramid_precis_creative_template/static/favicon_io/android-chrome-512x512.png
pyramid_precis_creative_template/static/favicon_io/apple-touch-icon.png
pyramid_precis_creative_template/static/favicon_io/favicon-16x16.png
pyramid_precis_creative_template/static/favicon_io/favicon-32x32.png
pyramid_precis_creative_template/static/favicon_io/favicon.ico
pyramid_precis_creative_template/static/favicon_io/site.webmanifest
pyramid_precis_creative_template/static/icomoon/fonts/icomoon.eot
pyramid_precis_creative_template/static/icomoon/fonts/icomoon.svg
pyramid_precis_creative_template/static/icomoon/fonts/icomoon.ttf
pyramid_precis_creative_template/static/icomoon/fonts/icomoon.woff
pyramid_precis_creative_template/static/icomoon/style.css
pyramid_precis_creative_template/static/vendor/bootstrap/css/bootstrap-grid.css
pyramid_precis_creative_template/static/vendor/bootstrap/css/bootstrap-grid.min.css
pyramid_precis_creative_template/static/vendor/bootstrap/css/bootstrap-reboot.css
pyramid_precis_creative_template/static/vendor/bootstrap/css/bootstrap-reboot.min.css
pyramid_precis_creative_template/static/vendor/bootstrap/css/bootstrap.css
pyramid_precis_creative_template/static/vendor/bootstrap/css/bootstrap.min.css
pyramid_precis_creative_template/static/vendor/bootstrap/js/bootstrap.bundle.js
pyramid_precis_creative_template/static/vendor/bootstrap/js/bootstrap.bundle.min.js
pyramid_precis_creative_template/static/vendor/bootstrap/js/bootstrap.js
pyramid_precis_creative_template/static/vendor/bootstrap/js/bootstrap.min.js
pyramid_precis_creative_template-0.2.2.dist-info/LICENSE
pyramid_precis_creative_template-0.2.2.dist-info/METADATA
pyramid_precis_creative_template-0.2.2.dist-info/WHEEL
pyramid_precis_creative_template-0.2.2.dist-info/entry_points.txt
pyramid_precis_creative_template-0.2.2.dist-info/RECORD
